{
    "0": "\ud83e\udd17 https://t.co/dJVI657AN6",
    "1": "Good morning\ud83d\ude18\ud83d\ude18\ud83d\ude18\ud83d\ude18 https://t.co/Hw9fhf298G",
    "2": "Good morning\ud83c\udf1e\ud83c\udf1e\ud83c\udf1e\ud83c\udf1e https://t.co/8kfsjdehFx",
    "3": "https://t.co/vl0ik7qewP",
    "4": "https://t.co/FAOlRGgCCI",
    "5": "https://t.co/etmIVJDR1Y",
    "6": "https://t.co/EwrkTb0sqY",
    "7": "https://t.co/05k1f4da0P",
    "8": "Good morning my all freind https://t.co/3cuYL9Ua40",
    "9": "https://t.co/9QhrkNriM7",
    "10": "https://t.co/3XgyocMoWL",
    "11": "https://t.co/QrDwSDFR9x"
}