{
    "0": "Good morning https://t.co/ll7GL9PBpl",
    "1": "Hum akele hai koi raat bitana chahta hai https://t.co/lKTuGOjaBp",
    "2": "Good morning ji https://t.co/ISuAiBJAr3",
    "3": "Aaj aapkaa irada kya hai mere sath dinner par chalo ge https://t.co/kvStmvxyq3",
    "4": "Koi humko gf banayega https://t.co/j5wkcryCle",
    "5": "#NewProfilePic https://t.co/ZAvj7xum3Z",
    "6": "Good morning https://t.co/r5x2rQRNhu",
    "7": "Good morning kaisi lag rahi hu https://t.co/B4QKNbtoPi",
    "8": "RT @Pragyad01: \u0915\u094b\u0908 \u092e\u0947\u0930\u0947 \u0938\u093e\u0925 \u0905\u092a\u0928\u093e \u0938\u092e\u092f \u092c\u093f\u0924\u093e\u0928\u093e \u091a\u093e\u0939\u0924\u093e \u0939\u0948 ....??\n \ud83e\udee6\u2764\ufe0f\ud83e\udee6\u2764\ufe0f https://t.co/Ea0vzdVhZY",
    "9": "Good morning https://t.co/Fjn5KVGlgb",
    "10": "Good morning https://t.co/s0j5HTjjPx",
    "11": "Good morning and Happy Wednesday \u263a\ufe0f\ud83c\udf39\ud83c\udf39 https://t.co/Cf3vIyrB7P",
    "12": "RT @Priya_1325: \u0906\u092a \u0932\u094b\u0917 \u0915\u0940 \u0915\u094b\u0908 \u0917\u0930\u094d\u0932\u092b\u094d\u0930\u0947\u0902\u0921 \u0939\u0948 \u092f\u093e \u092e\u0948\u0902 \u092c\u0928 \u091c\u093e\u090a ?\u2764\ufe0f\n\ud83d\udc49@Priya_1325 https://t.co/r0lYu2Plm6",
    "13": "Good morning https://t.co/DefDYKursd",
    "14": "Good morning https://t.co/MwBRkZIyaS",
    "15": "@Kajal4K Hi",
    "16": "Good morning https://t.co/dPslVmP1lN",
    "17": "RT @Pragyad01: \u0916\u0942\u092c \u0915\u0930\u0924\u093e \u0939\u0948, \u0935\u094b \u092e\u0947\u0930\u0947 \u091c\u093c\u0916\u094d\u092e \u0915\u093e \u0907\u0932\u093e\u091c \u0915\u0941\u0930\u0947\u0926 \u0915\u0930 \u0926\u0947\u0916 \u0932\u0947\u0924\u093e \u0939\u0948, \u0914\u0930 \u0915\u0939\u0924\u093e \u0939\u0948 \u0935\u0915\u094d\u0924 \u0932\u0917\u0947\u0917\u093e..\n#\u0936\u0941\u092d_\u0938\u0902\u0927\u094d\u092f\u093e \n\ud83d\udc95\ud83d\udc95\ud83d\udc95\ud83d\udc95\ud83d\udc95\ud83d\udc95\ud83d\udc95\ud83d\udc95\n@Pragyad01 https://t.\u2026",
    "18": "Good morning twitter https://t.co/FX4ouPGvSE",
    "19": "Mere sath kaun pina chahta hai https://t.co/aDHKLrsG0F",
    "20": "Good night https://t.co/5PSgRwCmZA",
    "21": "Mere sath raat kaun bitana chahta hai https://t.co/uGpArPv7SW",
    "22": "Good morning twitter https://t.co/dW1zTlEOCu",
    "23": "Hum akele hai koi aa raha hai kya https://t.co/9lOw8PjjW0"
}