{
    "0": "RT @manisha838: Say hi if I made you look https://t.co/FyJ6lj6TF1",
    "1": "RT @rinaku738892: I like married men\ud83d\udc96\ud83d\udd25\n\n#Facebook https://t.co/wf1uKdOani",
    "2": "RT @manisha838: Can I inbox you my number???? https://t.co/KwjJHcFYR1",
    "3": "Do you kiss me \ud83d\udc8b https://t.co/oDFAHDzq0O",
    "4": "RT @SumanRa91: Can I call you \ud83d\udcde https://t.co/SKN8ahi124",
    "5": "RT @Sofia93947: Say hi if I made you look https://t.co/oimVVCAMKm",
    "6": "Hii\n Do you like me.. https://t.co/UuZZjxvMH0",
    "7": "Hii\n Do you like me.. https://t.co/gNQ3ew3VzH",
    "8": "RT @nahi0910: Hii\n Do you like me.. https://t.co/jucmVWK7J3",
    "9": "RT @ananyas94: Hii\n Do you like me.. https://t.co/9W8NnmVBmX",
    "10": "I need a male best friend \u2661anyone? \ud83e\udd7a\u2665\ufe0f https://t.co/8iGAC1Oi4l",
    "11": "RT @aanya37888: I'm 50+\n\nCome to my house ji \ud83c\udfe1.....\u2763\ufe0f https://t.co/L28PGodKb5",
    "12": "Do you love me \u2763\ufe0f \ud83d\udc9d \n#Facebook https://t.co/s1Bgr3BtIK",
    "13": "Follow me I am newable https://t.co/osxtH8mP1d",
    "14": "RT @Sofia93947: Can we chat on WhatsApp??\n\u2764\ufe0f\u2763\ufe0f https://t.co/cWFHkijuk7",
    "15": "RT @nahi0910: Follow me i am newbie \u2665\ufe0f https://t.co/1fnUVKdMQ2",
    "16": "RT @ananyas94: Hii\n Do you like me.. https://t.co/pWHasvYqT0",
    "17": "Say hi if I made you look https://t.co/3HoTT2gJdL",
    "18": "Hiii ..\nWatsapp ya Facebook ? https://t.co/qhhOVgsEoL",
    "19": "RT @rinaku738892: Hii\n Do you like me.. https://t.co/ckzOnqNFZY",
    "20": "Can I inbox you my number???? https://t.co/oX2hbbk1Tv",
    "21": "I am 40...\nCome to my house jee \ud83c\udf39 https://t.co/QtjYm7Q1Zc",
    "22": "RT @anie32200: F**k it, sending my full tape\ud83c\udfa5 to everyone that says \u201chi\u201d https://t.co/WbNnu46Npw",
    "23": "RT @nahi0910: Hii\n Do you like me.. https://t.co/C6cbKAhKDf",
    "24": "RT @nahi0910: I need a male best friend \u2661anyone? \ud83e\udd7a\u2665\ufe0f https://t.co/rnXoro0ftx",
    "25": "RT @nahi0910: Say hi if I made you look https://t.co/zrfkumYYc3",
    "26": "RT @rinaku738892: Hii\n Do you like me.. https://t.co/ZvYvMyiHBl",
    "27": "RT @manisha838: Hii\n Do you like me.. https://t.co/v9Q06I9nYW",
    "28": "RT @manisha838: Say hi if I made you look https://t.co/j5im8GLxIF",
    "29": "RT @Sofia93947: Say hi if I made you look https://t.co/JL3NDIOgaP",
    "30": "RT @manisha838: I like married men\ud83d\udc96\ud83d\udd25\n\n#Facebook https://t.co/HihpvsjBdX",
    "31": "Hii\n Do you like me.. https://t.co/pd9TdwNtjJ",
    "32": "RT @nahi0910: Hii\n Do you like me.. https://t.co/aOdipUs2gw",
    "33": "RT @manisha838: Say hi if I made you look https://t.co/eNsuY0gDmC",
    "34": "Can I inbox you my number???? https://t.co/PzgIstvO3j",
    "35": "I like married men \ud83d\udc96\ud83d\udd25\n\n#Facebook https://t.co/xwfhcFuABq",
    "36": "RT @aanya37888: Say hi if I made you look https://t.co/XTW4eyJD4q",
    "37": "Hii\n Do you like me.. https://t.co/WSahNdkOqA",
    "38": "RT @anie32200: Put a \ud83d\udc30 and I\u2019ll DM you an Easter \ud83d\udc23 gift!! (Today only) https://t.co/ILhKIQNqBx",
    "39": "RT @manisha838: Say hi if I made you look https://t.co/G2eabxVdTg",
    "40": "RT @manisha838: Say hi if I made you look https://t.co/HYXahEtxlw",
    "41": "I need a bed partner \ud83d\udc96\ud83d\udc93 https://t.co/loqy5oSojF",
    "42": "RT @aanya37888: Hii\n Do you like me.. https://t.co/2ncvHococ7",
    "43": "RT @nahi0910: 1 am 45+.. friendship kroge... https://t.co/IyOVoSoL4O",
    "44": "Send me your number \u2665\ufe0f\n\n#Facebook https://t.co/r2R9GjiPll",
    "45": "Hii\n Do you like me.. https://t.co/7caAVGsI9P",
    "46": "RT @rinaku738892: Say hi if I made you look https://t.co/3ykRAcpdzd",
    "47": "RT @nahi0910: Hii\n Do you like me.. https://t.co/T0O7Qkhcxp",
    "48": "Say hi if I made you look https://t.co/HUjYfIqg12",
    "49": "RT @aanya37888: Say hi if I made you look https://t.co/FPUDVscIfy",
    "50": "RT @nahi0910: Say hi if I made you look https://t.co/bixPNeZOAd",
    "51": "RT @nahi0910: Hii\n Do you like me.. https://t.co/YsH6HkZKc7",
    "52": "RT @nahi0910: I need a male best friend \u2661anyone? \ud83e\udd7a\u2665\ufe0f https://t.co/zoodOxtjz0",
    "53": "can you kiss me \u2764\ufe0f\u2764\ufe0f\u2665\ufe0f https://t.co/HuNHjG33qO",
    "54": "Say hi if I made you look https://t.co/FyJ6lj6TF1",
    "55": "Are you 18+ ?\n\n#facebook https://t.co/BjdCVcFuHx",
    "56": "like married men \ud83d\ude0d\ud83d\udd25\n\n#Facebook https://t.co/bOjDyqIcwZ",
    "57": "I need a bed partner \ud83d\udc96\ud83d\udc93 https://t.co/Gab1FRx3qb",
    "58": "RT @anie32200: F**k it, sending my full tape\ud83c\udfa5 to everyone that says \u201chi\u201d https://t.co/JqVQh8cjCj",
    "59": "I need a bed partner \ud83d\udc96\ud83d\udc93 https://t.co/IYmbbMg62n",
    "60": "RT @Sofia93947: Can I inbox you my number???? https://t.co/CSiUJ7e5J1",
    "61": "RT @manisha838: Hii\n Do you like me.. https://t.co/wJcsLhoB55",
    "62": "Hii\n Do you like me https://t.co/YAsAwNm1I1",
    "63": "RT @RinaKum152: Can I call you \ud83d\udcde https://t.co/kbhXyfkmS7",
    "64": "Send me your number \ud83d\udcde https://t.co/kand52R0sT",
    "65": "RT @nahi0910: Hii\n Do you like me.. https://t.co/vjxA9jOPJH",
    "66": "RT @rinaku738892: I need a male best friend \u2661anyone? \ud83e\udd7a\u2665\ufe0f https://t.co/aLtnwdvZU6",
    "67": "RT @Sofia93947: 1 am 45+.. friendship kroge... https://t.co/9Fyyls1XA6",
    "68": "RT @Sofia93947: I'm 50+\n\nCome to my house ji \ud83c\udfe1.....\u2763\ufe0f https://t.co/FfRhnrqlaG",
    "69": "I like married men \ud83d\ude0d\ud83d\udd25\n\n#Facebook https://t.co/bBThR0KC8Q",
    "70": "Do you love me \ud83d\udc95\ud83d\udc97 https://t.co/TiPAV9tuGa",
    "71": "RT @Sofia93947: Say hi if I made you look https://t.co/LuTNmTtktJ",
    "72": "RT @aanya37888: Hii\n Do you like me.. https://t.co/C1f226MMWk",
    "73": "Do you love me \u2763\ufe0f \ud83d\udc9d \n#Facebook https://t.co/Edr4HpYuTU",
    "74": "I like married men \ud83d\udc96\ud83d\udd25\n\n#Facebook https://t.co/nZRi7Qie8s",
    "75": "RT @rinaku738892: Can we chat on WhatsApp??\n\u2764\ufe0f\u2763\ufe0f https://t.co/FzU01kLwRH",
    "76": "RT @Sofia93947: Say hi if I made you look https://t.co/XgUPIZDT7G",
    "77": "Can we chat on WhatsApp??\n\u2764\ufe0f\u2763\ufe0f https://t.co/QQJRfhuegO",
    "78": "RT @manisha838: 1 am 45+.. friendship kroge... https://t.co/Du8CpK2Hju",
    "79": "RT @rinaku738892: I need a male best friend \u2661anyone? \ud83e\udd7a\u2665\ufe0f https://t.co/gCXp3x9Ah2",
    "80": "Say hi if I made you look https://t.co/NInmi70KJs",
    "81": "RT @aanya37888: Hii\n Do you like me.. https://t.co/omnfuB4Uwh",
    "82": "I'm 50+\n\nCome to my house ji \ud83c\udfe1.....\u2763\ufe0f https://t.co/VX3RAgVX9N",
    "83": "Are you 18+ ?\n\n#Facebook https://t.co/hEQwRkA4rk",
    "84": "I am 20+ friendship kroge ji \u2665\ufe0f\u2665\ufe0f https://t.co/JvdOYmTPRf",
    "85": "Hii\n Do you like me.. https://t.co/TX28UxvM2y",
    "86": "RT @aanya37888: Say hi if I made you look https://t.co/Xg9dG9raHa",
    "87": "RT @manisha838: Say hi if I made you look https://t.co/HUjYfIqg12",
    "88": "RT @rinaku738892: I need a male best friend \u2661anyone? \ud83e\udd7a\u2665\ufe0f https://t.co/65x8oMdk28",
    "89": "Do you love me \u2764\ufe0f\ud83d\udc9e\n\n#kissme https://t.co/AWP8zANqQS",
    "90": "RT @muskan628801: Follow me i am newbie \u2665\ufe0f https://t.co/XBVkWjpJLc",
    "91": "RT @Sofia93947: Hii\n Do you like me.. https://t.co/THHqtyFqUR",
    "92": "RT @ananyas94: Say hi if I made you look https://t.co/ScMo6BNuXr",
    "93": "Hii\n Do you like me.. https://t.co/EJu5Dyb2i4",
    "94": "I am watching sex https://t.co/TpEfwL7RYf",
    "95": "I need a bed partner \ud83d\udc96\ud83d\udc93 https://t.co/6rud5ZHjiV",
    "96": "Good morning \ud83c\udf04 https://t.co/ywAnfMR6it",
    "97": "Hii\n Do you like me.. https://t.co/mT1DBgcQkc",
    "98": "RT @ananyas94: Hii\n Do you like me.. https://t.co/XGpwSvCSME",
    "99": "RT @ananyas94: Say hi if I made you look https://t.co/CunoOYVw0W",
    "100": "RT @ananyas94: I like married men\ud83d\udc96\ud83d\udd25\n\n#Facebook https://t.co/rbyriftVf1",
    "101": "RT @nahi0910: Hii\n Do you like me.. https://t.co/kcAQPoiwQh",
    "102": "RT @nahi0910: Say hi if I made you look https://t.co/3jhmWj3Fez",
    "103": "Hii\n Do you like me.. https://t.co/Q3ZRhznu3c",
    "104": "I'm 50+\n\nCome to my house ji \ud83c\udfe1.....\u2763\ufe0f https://t.co/hbpitziULp",
    "105": "RT @nahi0910: Hii\n Do you like me.. https://t.co/FHo7dINefu",
    "106": "Hii\n Do you like me.. https://t.co/XSHO6UoN7C",
    "107": "RT @Sofia93947: Hii\n Do you like me.. https://t.co/JfFEn3VX4J",
    "108": "RT @aanya37888: Say hi if I made you look https://t.co/1sbxYvXtf7",
    "109": "can you kiss me \u2764\ufe0f\u2764\ufe0f\u2665\ufe0f https://t.co/0dKEEnGrkb",
    "110": "RT @ananyas94: Say hi if I made you look https://t.co/EJtH2Zujqu",
    "111": "RT @aanya37888: Hii\n Do you like me.. https://t.co/pHoxxEPxZ0",
    "112": "RT @ananyas94: Can I inbox you my number???? https://t.co/B4DlBA5fcF",
    "113": "Do you like me \ud83d\udc4d\u2665\ufe0f https://t.co/djMDWsBVmH",
    "114": "Are you 18+ ?\n\n#Facebook https://t.co/ZGnkYLKKdf",
    "115": "RT @aanya37888: Say hi if I made you look https://t.co/YrCwYMywvu",
    "116": "RT @Sofia93947: I need a male best friend \u2661anyone? \ud83e\udd7a\u2665\ufe0f https://t.co/YihNkTlyaR",
    "117": "Can I call you\ud83d\udcde https://t.co/uQWSnR9eX0",
    "118": "RT @rinaku738892: Hii\n Do you like me.. https://t.co/pqjUlCuHaX",
    "119": "RT @rinaku738892: I need a male best friend \u2661anyone? \ud83e\udd7a\u2665\ufe0f https://t.co/50dnKOCyta",
    "120": "I need a male best friend \u2661anyone? https://t.co/9wrO3EQFoi",
    "121": "RT @ananyas94: Hii\n Do you like me.. https://t.co/wuFPW5W4Hd",
    "122": "Do you love me \u2764\ufe0f\ud83d\udc9e\n\n#kissme https://t.co/RBWn3upAFa",
    "123": "RT @Sofia93947: Say hi if I made you look https://t.co/egBVVcpFq7",
    "124": "Can I inbox you my number???? https://t.co/bSy35HJt5v",
    "125": "Can you inbox you number please \ud83e\udd7a https://t.co/IGef3LCmG7",
    "126": "RT @nahi0910: Say hi if I made you look https://t.co/UQTveTEwZn",
    "127": "RT @ananyas94: Can we chat on WhatsApp??\n\u2764\ufe0f\u2763\ufe0f https://t.co/yGg9FcloWV",
    "128": "RT @manisha838: Say hi if I made you look https://t.co/3HoTT2gJdL",
    "129": "RT @aanya37888: Say hi if I made you look https://t.co/gbcpyKuL8H",
    "130": "RT @rinaku738892: I need a male best friend \u2661anyone? \ud83e\udd7a\u2665\ufe0f https://t.co/PI8oh29Utz",
    "131": "RT @Sofia93947: Can you inbox you number please \ud83e\udd7a https://t.co/GxnwAaLSVz",
    "132": "RT @aanya37888: Say hi if I made you look https://t.co/6x0mKTdKqX",
    "133": "Do you love me \u2764\ufe0f\ud83d\udc9e\n\n#kissme https://t.co/4Z1ChjrBeY",
    "134": "RT @rinaku738892: I need a male best friend \u2661anyone? \ud83e\udd7a\u2665\ufe0f https://t.co/VlVxNggS49",
    "135": "RT @rinaku738892: Say hi if I made you look https://t.co/agFdAitPJ0",
    "136": "Are you 18+ ?\n\n#Facebook https://t.co/TiN7WOQ9Tb",
    "137": "Do you like me \ud83d\udc4d\u2665\ufe0f https://t.co/DsDBqmaLx7",
    "138": "RT @ananyas94: Say hi if I made you look https://t.co/O1Nq43fWMB",
    "139": "RT @manisha838: Hii\n Do you like me.. https://t.co/8R7GVocybY",
    "140": "Can I inbox you my number???? https://t.co/1jtfVTRXNo",
    "141": "Do you love me \u2764\ufe0f\ud83d\udc9e\n\n#kissme https://t.co/Gu5hp7Fyr8",
    "142": "Do you love me \u2764\ufe0f\ud83d\udc9e\n\n#kissme https://t.co/6brd5dstIW",
    "143": "RT @rinaku738892: Hii\n Do you like me.. https://t.co/rqRulaw8gk",
    "144": "RT @ananyas94: I need a male best friend \u2661anyone? \ud83e\udd7a\u2665\ufe0f https://t.co/HPGsBjAeDg",
    "145": "RT @aanya37888: Say hi if I made you look https://t.co/6KjXapGz24",
    "146": "RT @ananyas94: Hii\n Do you like me.. https://t.co/zsbi1cEDlG",
    "147": "Hii\n Do you like me.. https://t.co/v9Q06I9nYW",
    "148": "RT @manisha838: Can I inbox you my number???? https://t.co/PzgIstvO3j",
    "149": "RT @Sofia93947: Can I call you \ud83d\udcde https://t.co/WcJcx59Veo",
    "150": "Can I inbox you my number???? https://t.co/x2rfFYArZJ",
    "151": "RT @ananyas94: Say hi if I made you look https://t.co/8R2Lf13r6S",
    "152": "RT @nahi0910: Hii\n Do you like me.. https://t.co/tbw2VSKfEE",
    "153": "can you kiss me \u2764\ufe0f\u2764\ufe0f\u2665\ufe0f https://t.co/0nXKMNxgVY",
    "154": "RT @manisha838: Say hi if I made you look https://t.co/BWVC4y6PHJ",
    "155": "Can I inbox you my number???? https://t.co/4PFOKgTObP",
    "156": "RT @Sofia93947: Say hi if I made you look https://t.co/Mrn4xd4kdI",
    "157": "Hii\n Do you like me https://t.co/2SKhmVXxOo",
    "158": "Hii\n Do you like me.. https://t.co/VDfUwMsglr",
    "159": "Say hi if I made you look https://t.co/SlsmewYZjC",
    "160": "Hii\n Do you like me https://t.co/Xq5fGwKClJ",
    "161": "RT @ananyas94: Hii\n Do you like me.. https://t.co/X7uNbISoFf",
    "162": "RT @Sofia93947: I like married men\ud83d\udc96\ud83d\udd25\n\n#Facebook https://t.co/tYch0dDVoy",
    "163": "RT @nahi0910: Say hi if I made you look https://t.co/2hpvNJEKPE",
    "164": "RT @nahi0910: Can I inbox you my number???? https://t.co/BMYmY1d6tK",
    "165": "I need a male best friend \u2661anyone? \ud83e\udd7a\u2665\ufe0f https://t.co/Xr2RnXAkFa",
    "166": "\ud83d\udc96\ud83d\udc96Good Morning \ud83d\udc96 \ud83d\udc96 https://t.co/Z3Z3Kte7AU",
    "167": "Send me your number \u2665\ufe0f\n\n#Facebook https://t.co/GG4iOw1jTT",
    "168": "I need a male best friend \u2661anyone? \ud83e\udd7a\u2665\ufe0f https://t.co/8a1N1hpTdO",
    "169": "Do you love me \u2764\ufe0f\ud83d\udc9e\n\n#kissme https://t.co/XpxO2GY42K",
    "170": "RT @aanya37888: Say hi if I made you look https://t.co/BhKmJgsEaY",
    "171": "RT @manisha838: Hii\n Do you like me.. https://t.co/7caAVGsI9P",
    "172": "Hii\n Do you like me.. https://t.co/uAucqjx5Cb",
    "173": "RT @manisha838: I need a male best friend \u2661anyone? \ud83e\udd7a\u2665\ufe0f https://t.co/8iGAC1Oi4l",
    "174": "RT @ananyas94: Can we chat on WhatsApp??\n\u2764\ufe0f\u2763\ufe0f https://t.co/Q9XyvcokOq",
    "175": "RT @Sofia93947: Say hi if I made you look https://t.co/MHozc4WifH",
    "176": "RT @manisha838: Hii\n Do you like me.. https://t.co/TX28UxvM2y",
    "177": "Hiii ..\nWatsapp ya Facebook? https://t.co/ceTi2lx5oR",
    "178": "Send me your number ?\n\n#facebook https://t.co/7t0i5RWhnq",
    "179": "RT @Sofia93947: Hii\n Do you like me.. https://t.co/n6ez4N8Q8a",
    "180": "Hii\n Do you like me.. https://t.co/MrJM4e6Grz",
    "181": "RT @ananyas94: Say hi if I made you look https://t.co/AW09kNcXXe",
    "182": "Hii\n Do you like me.. https://t.co/YdCTvWXbpQ",
    "183": "Hii\n Do you like me.. https://t.co/wJcsLhoB55",
    "184": "RT @rinaku738892: Hii\n Do you like me.. https://t.co/1fDejYLXVB",
    "185": "RT @manisha838: I need a male best friend \u2661anyone? \ud83e\udd7a\u2665\ufe0f https://t.co/Xr2RnXAkFa",
    "186": "RT @nahi0910: Say hi if I made you look https://t.co/ltvYYSx5t4",
    "187": "RT @Sofia93947: Say hi if I made you look https://t.co/TVEbLIdddM",
    "188": "I need a bed partner \ud83d\udc96\ud83d\udc93 https://t.co/GtYdvYcMR7",
    "189": "RT @Sofia93947: Hii\n Do you like me.. https://t.co/CjuC50OIde",
    "190": "Hii\n Do you like me.. https://t.co/KcZ9x0PH0n",
    "191": "RT @ananyas94: Hii\n Do you like me.. https://t.co/FRsCkL4JQR",
    "192": "Say hi if I made you look https://t.co/7AGvOIuQHw",
    "193": "Hii\n Do you like me.. https://t.co/bqQNZZuTNr",
    "194": "RT @ananyas94: Can I inbox you my number???? https://t.co/YUasUTXUn3",
    "195": "RT @RinaKum152: Can I call you \ud83d\udcde https://t.co/p3CcigUheW",
    "196": "Can you kiss me\ud83d\udc8b https://t.co/8QzQgF6rhA",
    "197": "RT @Sofia93947: Say hi if I made you look https://t.co/N4ifFPKa20",
    "198": "https://t.co/xKei4qM5rL",
    "199": "I need a bed partner \ud83d\udc96\ud83d\udc93 https://t.co/46Hi6sjSys",
    "200": "RT @manisha838: Say hi if I made you look https://t.co/Du28rgFx01",
    "201": "Hello jii\nI want to kiss you \ud83d\udc8b https://t.co/HsWfAGIzTK",
    "202": "RT @anie32200: Put a \ud83d\udc30 and I\u2019ll DM you an Easter \ud83d\udc23 gift!! (Today only) https://t.co/ATPUutMu1G",
    "203": "RT @rinaku738892: Can you inbox you number please \ud83e\udd7a https://t.co/O12mk0feWq",
    "204": "RT @manisha838: Say hi if I made you look https://t.co/oUCrMSyO13",
    "205": "RT @rinaku738892: I need a male best friend \u2661anyone? \ud83e\udd7a\u2665\ufe0f https://t.co/vxTMTLD5yd",
    "206": "RT @ananyas94: Say hi if I made you look https://t.co/eKl0GsAaJW",
    "207": "I like married men \ud83d\udc96\ud83d\udd25\n\n#Facebook https://t.co/0PNh0CnHRz",
    "208": "RT @Sofia93947: Say hi if I made you look https://t.co/KKM2XFgcAU",
    "209": "Say hi if I made you look https://t.co/3gRv8DaZTX",
    "210": "Can I inbox you my number???? https://t.co/QR0uz9wbH2",
    "211": "I need a bed partner \ud83d\udc96\ud83d\udc93 https://t.co/zBGhFeRZj1",
    "212": "Do you love me \u2764\ufe0f\ud83d\udc9e\n\n#kissme https://t.co/WpFbSMO48w",
    "213": "RT @ananyas94: Hii\n Do you like me.. https://t.co/oMJyRvsHa5",
    "214": "Can we chat on WhatsApp??\n\u2764\ufe0f\u2763\ufe0f https://t.co/IwpoHBFY6B",
    "215": "Hii\n Do you like me https://t.co/hYQRNaDaiq",
    "216": "Say hi if I made you look https://t.co/oUCrMSyO13",
    "217": "RT @rinaku738892: Hii\n Do you like me.. https://t.co/RrKCk70vMR",
    "218": "RT @rinaku738892: Say hi if I made you look https://t.co/ZmDn79Oq0w",
    "219": "RT @rinaku738892: Can we chat on WhatsApp??\n\u2764\ufe0f\u2763\ufe0f https://t.co/kP8cBTeW6b",
    "220": "RT @ananyas94: I need a male best friend \u2661anyone? \ud83e\udd7a\u2665\ufe0f https://t.co/pvhEBEXBCo",
    "221": "RT @Sofia93947: Say hi if I made you look https://t.co/8zfYLjo9iX",
    "222": "RT @aanya37888: Say hi if I made you look https://t.co/oR9CYE9bOq",
    "223": "RT @rinaku738892: Hii\n Do you like me.. https://t.co/U6zoHTFCqI",
    "224": "Are you 18+ ?\n\n#Facebook https://t.co/2AgfDqTIq1",
    "225": "RT @manisha838: Say hi if I made you look https://t.co/eBy6Ml4TCr",
    "226": "RT @ananyas94: Hii\n Do you like me.. https://t.co/qPAoE1sjKg",
    "227": "RT @aanya37888: Hii\n Do you like me.. https://t.co/1AFxT90Imm",
    "228": "Say hi if I made you look https://t.co/olQuetNPFv",
    "229": "RT @manisha838: Say hi if I made you look https://t.co/NInmi70KJs",
    "230": "RT @Sofia93947: Can I inbox you my number???? https://t.co/3oxIFvdJUF",
    "231": "RT @ananyas94: Say hi if I made you look https://t.co/0hBGVBORbH",
    "232": "RT @manisha838: Say hi if I made you look https://t.co/R0PlmM6a39",
    "233": "Can I inbox you my number???? https://t.co/K5oULWl8O0",
    "234": "Say hi if I made you look https://t.co/h2JPE2KYj7",
    "235": "RT @rinaku738892: Can I inbox you my number???? https://t.co/dER8IsuFlW",
    "236": "RT @rinaku738892: Hii\n Do you like me.. https://t.co/NOCtS23anH",
    "237": "Are you 18+ ?\n\n#Facebook https://t.co/tudER4UG13",
    "238": "can you kiss me \u2764\ufe0f\u2764\ufe0f\u2665\ufe0f https://t.co/C0OMr5SyQg",
    "239": "RT @aanya37888: Can you inbox you number please \ud83e\udd7a https://t.co/017ZTL3lG9",
    "240": "RT @manisha838: https://t.co/xKei4qM5rL",
    "241": "RT @rinaku738892: Hii\n Do you like me.. https://t.co/wpS0JNVE95",
    "242": "Send me your number ?\n\n#facebook https://t.co/46BeVCSIWo",
    "243": "RT @nahi0910: Hii\n Do you like me.. https://t.co/dxuwua4rmo",
    "244": "RT @Sofia93947: Can I inbox you my number???? https://t.co/jk5FLADgsG",
    "245": "Are you 18+ ?\n\n#Facebook https://t.co/xNXrYA5CW6",
    "246": "Are you 18+ ?\n\n#Facebook https://t.co/bSwOMnfGcr",
    "247": "RT @Sofia93947: Say hi if I made you look https://t.co/uCdreg40b2",
    "248": "Are you 18+ ?\n\n#Facebook https://t.co/COpBF0J54b",
    "249": "1 am 45+.. friendship kroge... https://t.co/VWAzYQYpdR",
    "250": "Do you love me \u2764\ufe0f\ud83d\udc9e\n\n#kissme https://t.co/PM4JTcTht6",
    "251": "RT @manisha838: Say hi if I made you look https://t.co/y21dwbpnpQ",
    "252": "RT @aanya37888: I need a male best friend \u2661anyone? \ud83e\udd7a\u2665\ufe0f https://t.co/0MjTYppTSz",
    "253": "RT @aanya37888: Hii\n Do you like me.. https://t.co/BQy41TNjSv",
    "254": "RT @manisha838: Say hi if I made you look https://t.co/XluMVJE4Ml",
    "255": "Do you love me \u2764\ufe0f\ud83d\udc9e\n\n#kissme https://t.co/92qn7KOfmf",
    "256": "RT @ananyas94: Hii\n Do you like me.. https://t.co/toZBZqMwEr",
    "257": "RT @aanya37888: Hii\n Do you like me.. https://t.co/EIgyiqOOBC",
    "258": "RT @nahi0910: Say hi if I made you look https://t.co/xJKLtGRZfC",
    "259": "RT @ananyas94: Say hi if I made you look https://t.co/ZePYQmTGn9",
    "260": "RT @aanya37888: Can we chat on WhatsApp??\n\u2764\ufe0f\u2763\ufe0f https://t.co/PKPiYTJ6Z3",
    "261": "Can I inbox you my number???? https://t.co/M9uChFwNRI",
    "262": "Meri chut lena chahoge https://t.co/vnTqeEuAxs",
    "263": "Hii\n Do you like me.. https://t.co/xZikGbOqVX",
    "264": "I need a HOT bedroom partner\ud83d\udd25\ud83d\udd25\ud83d\ude48 https://t.co/2W6wYhSfdl",
    "265": "Hii\n Do you like me https://t.co/8LSSDQCfdf",
    "266": "Are you 18+ ?\n\n#Facebook https://t.co/1b9d14RLls",
    "267": "Can I kiss you \ud83d\udc8b https://t.co/8K1YJBsbOB",
    "268": "Hii\n Do you like me.. https://t.co/l8hQo5cTWJ",
    "269": "I'm 50+\n\nCome to my house ji \ud83c\udfe1.....\u2763\ufe0f https://t.co/cWz4wawrgR",
    "270": "RT @nahi0910: I like married men\ud83d\udc96\ud83d\udd25\n\n#Facebook https://t.co/9yJUJD6W37",
    "271": "Send me your number \ud83d\udcde https://t.co/oPrDceFv5h",
    "272": "Say hi if I made you look https://t.co/1vA4JU7AH8",
    "273": "RT @aanya37888: Say hi if I made you look https://t.co/J1g3MJwTuj",
    "274": "RT @ananyas94: Can I inbox you my number???? https://t.co/tqJ2lZx0e2",
    "275": "RT @nahi0910: Hii\n Do you like me.. https://t.co/Wan513bUkT",
    "276": "RT @manisha838: I'm 50+\n\nCome to my house ji \ud83c\udfe1.....\u2763\ufe0f https://t.co/1iyKi06IoN",
    "277": "RT @aanya37888: Can we chat on WhatsApp??\n\u2764\ufe0f\u2763\ufe0f https://t.co/yHPeQxkbNJ",
    "278": "RT @aanya37888: Say hi if I made you look https://t.co/Yc5qqqNvwS",
    "279": "RT @nahi0910: I need a male best friend \u2661anyone? \ud83e\udd7a\u2665\ufe0f https://t.co/T1k6RnIXcE",
    "280": "RT @rinaku738892: Hii\n Do you like me.. https://t.co/IYjF2dKZJI",
    "281": "RT @nahi0910: Say hi if I made you look https://t.co/YgacZlj3Rm",
    "282": "Do you love me \u2763\ufe0f \ud83d\udc9d \n#Facebook https://t.co/gxifONHV7g",
    "283": "RT @nahi0910: Can I inbox you my number???? https://t.co/JWZLDyEkOi",
    "284": "Hii\n Do you like me.. https://t.co/tRh1nCFzKk",
    "285": "RT @nahi0910: Can I inbox you my number???? https://t.co/y7T9sSiRm4",
    "286": "RT @manisha838: Say hi if I made you look https://t.co/1vA4JU7AH8",
    "287": "I need a male best friend \u2661anyone? \ud83e\udd7a\u2665\ufe0f https://t.co/vcwo5fu89L",
    "288": "RT @rinaku738892: Hii\n Do you like me.. https://t.co/VY3rm11Boj",
    "289": "You can enjoy with me \ud83d\udc93 https://t.co/UWUrbI8HHZ",
    "290": "RT @manisha838: Hii\n Do you like me.. https://t.co/JVuFMY77Pn",
    "291": "RT @manisha838: Say hi if I made you look https://t.co/olQuetNPFv",
    "292": "RT @Sofia93947: Hii\n Do you like me.. https://t.co/X0EylJsBjq",
    "293": "RT @rinaku738892: Can we chat on WhatsApp??\n\u2764\ufe0f\u2763\ufe0f https://t.co/iawlZizYFG",
    "294": "RT @ananyas94: Hii\n Do you like me.. https://t.co/fzs9KsE9hf",
    "295": "I need a bed partner \ud83d\udc96\ud83d\udc93 https://t.co/K8HM4fxkxy",
    "296": "RT @Sofia93947: 1 am 45+.. friendship kroge... https://t.co/BrmXDGe47p",
    "297": "RT @aanya37888: Say hi if I made you look https://t.co/jGhJsOksm9",
    "298": "1 am 45+.. friendship kroge... https://t.co/28bhxmNhzS",
    "299": "RT @Sofia93947: Say hi if I made you look https://t.co/kJR7zwIOFh",
    "300": "RT @manisha838: Say hi if I made you look https://t.co/3gRv8DaZTX",
    "301": "Say hi if I made you look https://t.co/y21dwbpnpQ",
    "302": "Can I inbox you my number???? https://t.co/4dVUx71DwK",
    "303": "RT @ananyas94: Say hi if I made you look https://t.co/gSUci3DLOg",
    "304": "I need a bed partner \ud83d\udc96\ud83d\udc93 https://t.co/bu62FXbGJA",
    "305": "RT @aanya37888: Say hi if I made you look https://t.co/oaiGYIp09s",
    "306": "RT @nahi0910: Say hi if I made you look https://t.co/83w0wWqom2",
    "307": "RT @rinaku738892: Hii\n Do you like me.. https://t.co/VzD3DJ3p92",
    "308": "\ud83d\udc96\ud83d\udc96Good Morning \ud83d\udc96 \ud83d\udc96 https://t.co/gAcMwFmPHk",
    "309": "RT @anie32200: F**k it, sending my full tape\ud83c\udfa5 to everyone that says \u201chi\u201d https://t.co/bRLu3UhIS3",
    "310": "RT @aanya37888: Hii\n Do you like me.. https://t.co/XRFtvZcRI0",
    "311": "Send me your number \u2665\ufe0f\n\n#Facebook https://t.co/Io9nHxyaQ8",
    "312": "RT @Sofia93947: Hii\n Do you like me.. https://t.co/XFDyTLDKti",
    "313": "RT @ananyas94: Can you inbox you number please \ud83e\udd7a https://t.co/SLTuGYMwZa",
    "314": "I need a HOT bedroom partner\ud83d\udd25\ud83d\udd25\ud83d\ude48 https://t.co/iNsU4R9wsQ",
    "315": "RT @manisha838: Can I call you \ud83d\udcde https://t.co/YhMPBeeLB8",
    "316": "Hii\n Do you like me.. https://t.co/JVuFMY77Pn",
    "317": "can you kiss me \u2764\ufe0f\u2764\ufe0f\u2665\ufe0f https://t.co/g5H000R1K6",
    "318": "Hii\n Do you like me.. https://t.co/arWG6IENfy",
    "319": "Hii\n Do you like me.. https://t.co/GjJ9BMQQgQ",
    "320": "Send me your number \ud83d\udcde https://t.co/5HLDIsMIz0",
    "321": "Can I inbox you my number???? https://t.co/KwjJHcFYR1",
    "322": "RT @rinaku738892: Can I inbox you my number???? https://t.co/HdPC8FmYdF",
    "323": "RT @manisha838: Hii\n Do you like me.. https://t.co/gNQ3ew3VzH",
    "324": "RT @aanya37888: I'm 50+\n\nCome to my house ji \ud83c\udfe1.....\u2763\ufe0f https://t.co/SkoZ9GkOPy",
    "325": "can you kiss me \u2764\ufe0f\u2764\ufe0f\u2665\ufe0f https://t.co/D7lI9Xna3J",
    "326": "RT @nahi0910: Say hi if I made you look https://t.co/gG8xn8V1n4",
    "327": "Show this to your Mom!!!! https://t.co/vSrxVu7VKA",
    "328": "RT @Sofia93947: I need a male best friend \u2661anyone? \ud83e\udd7a\u2665\ufe0f https://t.co/sFHnyQuch1",
    "329": "Do you love me \u2764\ufe0f\ud83d\udc9e\n\n#kissme https://t.co/gsJu1iCjCg",
    "330": "Are you 18+ ?\n\n#Facebook https://t.co/sK9FEPvxLf",
    "331": "Do you love me \u2763\ufe0f \ud83d\udc9d \n#Facebook https://t.co/KM0IIbXpFf",
    "332": "RT @aanya37888: I need a male best friend \u2661anyone? \ud83e\udd7a\u2665\ufe0f https://t.co/tn3uNL58O0",
    "333": "Say hi if I made you look https://t.co/G2eabxVdTg",
    "334": "RT @rinaku738892: Say hi if I made you look https://t.co/vDFkyzjfLC",
    "335": "RT @manisha838: Hii\n Do you like me.. https://t.co/0KztqWDxHQ",
    "336": "Send me your number \u2665\ufe0f\n\n#Facebook https://t.co/xtRnPfEJaj",
    "337": "RT @anie32200: F**k it, sending my full tape\ud83c\udfa5 to everyone that says \u201chi\u201d https://t.co/UPebfuGA8s",
    "338": "Say hi if I made you look https://t.co/eNsuY0gDmC",
    "339": "RT @Sofia93947: Can we chat on WhatsApp??\n\u2764\ufe0f\u2763\ufe0f https://t.co/i9C82sGDbi",
    "340": "Hiii ..\nWatsapp ya Facebook? https://t.co/kPyw8EI8dY",
    "341": "RT @rinaku738892: I need a male best friend \u2661anyone? \ud83e\udd7a\u2665\ufe0f https://t.co/beG0AVOm1P",
    "342": "Are you 18+ ?\n\n#facebook https://t.co/yOsBrdzFtY",
    "343": "RT @aanya37888: Can I inbox you my number???? https://t.co/cgdtASy7VM",
    "344": "Do you love me \u2764\ufe0f\ud83d\udc9e\n\n#kissme https://t.co/1jWQNfeWEp",
    "345": "Do you love me \u2764\ufe0f\ud83d\udc9e\n\n#kissme https://t.co/BH9SLIkAvi",
    "346": "RT @nahi0910: Can we chat on WhatsApp??\n\u2764\ufe0f\u2763\ufe0f https://t.co/On67snj1qZ",
    "347": "RT @nahi0910: Say hi if I made you look https://t.co/LVTkyta74T",
    "348": "RT @Sofia93947: Say hi if I made you look https://t.co/x8y42DHhs9",
    "349": "RT @ananyas94: Say hi if I made you look https://t.co/iDXdysqCpn",
    "350": "RT @rinaku738892: Say hi if I made you look https://t.co/T9QzcE4hlA",
    "351": "RT @manisha838: Say hi if I made you look https://t.co/gv8oYRMSEr",
    "352": "RT @nahi0910: Say hi if I made you look https://t.co/2Roqh1XJe4",
    "353": "RT @anie32200: Say 'yes' if you see this and want the \ud83c\udf36\ufe0f version in DMs https://t.co/hThjZhQMBk",
    "354": "RT @Sofia93947: Say hi if I made you look https://t.co/4i1rufJqpx",
    "355": "RT @rinaku738892: Say hi if I made you look https://t.co/UkkUKPvNit",
    "356": "RT @ananyas94: Say hi if I made you look https://t.co/VRl9eCJyrV",
    "357": "RT @nahi0910: Say hi if I made you look https://t.co/jW0pmZwq1R",
    "358": "RT @Sofia93947: Hii\n Do you like me.. https://t.co/uS3zvpdWCr",
    "359": "RT @AnuBhar04: Can I call you \ud83d\udcde https://t.co/EFoEn3fbvv",
    "360": "RT @nahi0910: Say hi if I made you look https://t.co/jtsu1pa349",
    "361": "RT @rinaku738892: Can I inbox you my number???? https://t.co/fRdoQaVfZs",
    "362": "1 am 45+.. friendship kroge... https://t.co/Du8CpK2Hju",
    "363": "1 am 45+.. friendship kroge... https://t.co/HxaKOQrf0y",
    "364": "Say hi if I made you look https://t.co/HYXahEtxlw",
    "365": "Do you love me \u2764\ufe0f\ud83d\udc9e\n\n#kissme https://t.co/CxrV9GmMRQ",
    "366": "RT @manisha838: Hii\n Do you like me.. https://t.co/4tOYw0XGUe",
    "367": "Do you love me \u2764\ufe0f\ud83d\udc9e\n\n#kissme https://t.co/4EGDoGlpwQ",
    "368": "RT @rinaku738892: Say hi if I made you look https://t.co/sEOS4goJa0",
    "369": "RT @rinaku738892: Say hi if I made you look https://t.co/KdGXHkC5P5",
    "370": "RT @manisha838: Hii\n Do you like me.. https://t.co/GjJ9BMQQgQ",
    "371": "RT @aanya37888: Hii\n Do you like me.. https://t.co/I7ejsT3n9U",
    "372": "RT @ananyas94: Hii\n Do you like me.. https://t.co/wKpNyDVD0M",
    "373": "I need a bed partner \ud83d\udc96\ud83d\udc93 https://t.co/uL5NEAfvLj",
    "374": "RT @nahi0910: Can you inbox you number please \ud83e\udd7a https://t.co/716us709Y4",
    "375": "RT @Sofia93947: Can I inbox you my number???? https://t.co/kAAOa9akNy",
    "376": "Hiii ..\nWatsapp ya Facebook? https://t.co/Eb4cRTuVSG",
    "377": "RT @manisha838: Hii\n Do you like me.. https://t.co/Q3ZRhznu3c",
    "378": "RT @ananyas94: Say hi if I made you look https://t.co/oMFddr77Qo",
    "379": "Hii\n Do you like me.. https://t.co/lcAERBeFSq",
    "380": "RT @manisha838: I'm 50+\n\nCome to my house ji \ud83c\udfe1.....\u2763\ufe0f https://t.co/hbpitziULp",
    "381": "Do you love me \u2764\ufe0f\ud83d\udc9e\n\n#kissme https://t.co/TjM5IH1jWK",
    "382": "Send me your number \u2665\ufe0f\n\n#Facebook https://t.co/OKpRs7IsK3",
    "383": "RT @nahi0910: Hii\n Do you like me.. https://t.co/aJYm9DRkqj",
    "384": "RT @PihuRan6: Can I call you \ud83d\udcde https://t.co/4kBgqUeo2x",
    "385": "RT @nahi0910: Say hi if I made you look https://t.co/FbQBY8LvVM",
    "386": "Are you 18+ ?\n\n#Facebook https://t.co/Y5PhSA18ov",
    "387": "I need a HOT bedroom partner\ud83d\udd25\ud83d\udd25\ud83d\ude48 https://t.co/3SWEawzHUY",
    "388": "I'm 50+\n\nCome to my house ji \ud83c\udfe1.....\u2763\ufe0f https://t.co/1iyKi06IoN",
    "389": "Hii\n Do you like me https://t.co/02xSs7Nmbo",
    "390": "Hiii https://t.co/KXNhapZmmT",
    "391": "Do you love me \u2764\ufe0f\ud83d\udc9e\n\n#kissme https://t.co/WkaVhzpcy3",
    "392": "Are you 18+ ?\n\n#Facebook https://t.co/p8ncVfRKvF",
    "393": "RT @aanya37888: Hii\n Do you like me.. https://t.co/yz4S6Themb",
    "394": "Do you like me \ud83d\udc4d\u2665\ufe0f https://t.co/aKpiXXbA30",
    "395": "RT @aanya37888: Hii\n Do you like me.. https://t.co/kZ8eQeCbpP",
    "396": "RT @ananyas94: Say hi if I made you look https://t.co/VpqeXDMw90",
    "397": "Hii\n Do you like me.. https://t.co/AKbB6Cyjv7",
    "398": "Hii\n Do you like me.. https://t.co/1OG38rC9Qn",
    "399": "Hii...\nDo you like me \ud83e\udd70 https://t.co/29TJUKYa0B",
    "400": "RT @manisha838: Hii\n Do you like me.. https://t.co/MrJM4e6Grz",
    "401": "can you kiss me \u2764\ufe0f\u2764\ufe0f\u2665\ufe0f https://t.co/tamwK44uaN",
    "402": "RT @aanya37888: Say hi if I made you look https://t.co/vVFZmT9hHN",
    "403": "Are you 18+ ?\n\n#Facebook https://t.co/vbTr4pnf9f",
    "404": "Are you 18+ ?\n\n#Facebook https://t.co/sdu9bd0mfE",
    "405": "Do you love me \u2764\ufe0f\ud83d\udc9e\n\n#kissme https://t.co/U8yrJMyhv1",
    "406": "RT @Sofia93947: Can we chat on WhatsApp??\n\u2764\ufe0f\u2763\ufe0f https://t.co/m5LWRI04U8",
    "407": "RT @Sofia93947: Hii\n Do you like me.. https://t.co/4p9oBZeCw0",
    "408": "Hii\n Do you like me https://t.co/UTaGczjnTG",
    "409": "RT @nahi0910: I'm 50+\n\nCome to my house ji \ud83c\udfe1.....\u2763\ufe0f https://t.co/VTSyaWrw0B",
    "410": "Hii\n Do you like me.. https://t.co/0KztqWDxHQ",
    "411": "RT @aanya37888: Hii\n Do you like me.. https://t.co/lrE1hlafq3",
    "412": "RT @aanya37888: 1 am 45+.. friendship kroge... https://t.co/8X1IHgnz5l",
    "413": "Hii\n Do you like me.. https://t.co/N8x3Y4v0uv",
    "414": "RT @Sofia93947: Say hi if I made you look https://t.co/m8wlJunpgn",
    "415": "RT @ananyas94: Say hi if I made you look https://t.co/fSN4Xb9o3n",
    "416": "I need a bed partner \ud83d\udc96\ud83d\udc93 https://t.co/To0h0UIgMX",
    "417": "Do you love me \u2764\ufe0f\ud83d\udc9e\n\n#kissme https://t.co/JoO3vHrBtM",
    "418": "Send me your number \u2665\ufe0f\n\n#Facebook https://t.co/iGk9ZU7MuE",
    "419": "Can I inbox you my number???? https://t.co/sSwvdplXc8",
    "420": "Hii\n Do you like me https://t.co/dknDpJ4tUt",
    "421": "RT @rinaku738892: I need a male best friend \u2661anyone? \ud83e\udd7a\u2665\ufe0f https://t.co/yCi0lFB8Wa",
    "422": "RT @Sofia93947: Say hi if I made you look https://t.co/ukY3hLwKyn",
    "423": "RT @rinaku738892: I need a male best friend \u2661anyone? \ud83e\udd7a\u2665\ufe0f https://t.co/CFAIbsVE9c",
    "424": "RT @ananyas94: Can we chat on WhatsApp??\n\u2764\ufe0f\u2763\ufe0f https://t.co/dqUa2TkNmf",
    "425": "Hii\n Do you like me.. https://t.co/b1z5fbUipg",
    "426": "RT @Sofia93947: Hii\n Do you like me.. https://t.co/oyLNIT4QSn",
    "427": "RT @Sofia93947: Hii\n Do you like me.. https://t.co/KI8fyEvfZs",
    "428": "RT @rinaku738892: Hii\n Do you like me.. https://t.co/n3M70YLcHQ",
    "429": "RT @manisha838: Say hi if I made you look https://t.co/7AGvOIuQHw",
    "430": "RT @manisha838: Can you inbox you number please \ud83e\udd7a https://t.co/IGef3LCmG7",
    "431": "RT @rinaku738892: 1 am 45+.. friendship kroge... https://t.co/LR1sHm8dS4",
    "432": "Hii\n Do you like me https://t.co/unxrllfWIs",
    "433": "RT @rinaku738892: Hii\n Do you like me.. https://t.co/pPFRbfKe17",
    "434": "Do you love me \u2764\ufe0f\ud83d\udc9e\n\n#kissme https://t.co/53nouuZ8jQ",
    "435": "RT @Sofia93947: I need a male best friend \u2661anyone? \ud83e\udd7a\u2665\ufe0f https://t.co/hERf4TIrhJ",
    "436": "Hii\n Do you like me https://t.co/LSNHp1rBHg",
    "437": "Hii\n Do you like me.. https://t.co/oQ5UbIT1QO",
    "438": "RT @Sofia93947: Hii\n Do you like me.. https://t.co/zIIyAIVwBa",
    "439": "Hii\n Do you like me.. https://t.co/trxbs0q0XF",
    "440": "Hii https://t.co/d6XRKKlkW5",
    "441": "RT @Sofia93947: Hii\n Do you like me.. https://t.co/oIVGe0Rrem",
    "442": "Hii\n Do you like me https://t.co/gGH7qdOT6o",
    "443": "Do you love me \u2764\ufe0f\ud83d\udc9e\n\n#kissme https://t.co/ThPniEsdC6",
    "444": "RT @nahi0910: Can we chat on WhatsApp??\n\u2764\ufe0f\u2763\ufe0f https://t.co/VrLbByVSJt",
    "445": "RT @Sofia93947: I'm 50+\n\nCome to my house ji \ud83c\udfe1.....\u2763\ufe0f https://t.co/GzKxtWYWyW",
    "446": "RT @manisha838: Can we chat on WhatsApp??\n\u2764\ufe0f\u2763\ufe0f https://t.co/IwpoHBFY6B",
    "447": "RT @rinaku738892: I need a male best friend \u2661anyone? \ud83e\udd7a\u2665\ufe0f https://t.co/NKRW2idyNS",
    "448": "Hii\n Do you like me.. https://t.co/X1qU4bgXBm",
    "449": "Call me \ud83e\udd19\ud83d\udcde https://t.co/OeDZ4qTOwO",
    "450": "RT @rinaku738892: Hii\n Do you like me.. https://t.co/j4cHyuyt4B",
    "451": "RT @ananyas94: Say hi if I made you look https://t.co/tP7PI3ya5x",
    "452": "Can I inbox you my number???? https://t.co/LCu7Rt4xKK",
    "453": "Hii\n Do you like me https://t.co/5lxQMxmgh2",
    "454": "Send me your number \u2665\ufe0f\n\n#Facebook https://t.co/I84IWkeXU7",
    "455": "I like married men\ud83d\udc96\ud83d\udd25\n\n#Facebook https://t.co/HihpvsjBdX",
    "456": "RT @Sofia93947: Hii\n Do you like me.. https://t.co/W31y7p0ikM",
    "457": "Say hi if I made you look https://t.co/eBy6Ml4TCr",
    "458": "RT @aanya37888: Say hi if I made you look https://t.co/nGqmP9lhJh",
    "459": "RT @Sofia93947: Say hi if I made you look https://t.co/ioECCfSyVJ",
    "460": "Hiii.........,\u2665\ufe0f\n\n#Facebook https://t.co/5wWXUGZ87R",
    "461": "Say hi if I made you look https://t.co/gv8oYRMSEr",
    "462": "RT @rinaku738892: I need a male best friend \u2661anyone? \ud83e\udd7a\u2665\ufe0f https://t.co/uBCuzyp6hj",
    "463": "RT @ananyas94: 1 am 45+.. friendship kroge... https://t.co/stiC4EJVX4",
    "464": "RT @Sofia93947: sending the full vid to everyone who says \u2018gn\u2019 https://t.co/AU1MITzA0A",
    "465": "RT @nahi0910: Can I inbox you my number???? https://t.co/GRBaEJ2EWO",
    "466": "1 am 25+.. friendship kroge... https://t.co/ersGEAy7FJ",
    "467": "Are you 18+ ?\n\n#Facebook https://t.co/VP9OnWmMEc",
    "468": "Do you like me \ud83d\udc4d\u2665\ufe0f https://t.co/Kz5MOD0Z05",
    "469": "RT @Sofia93947: Hii\n Do you like me.. https://t.co/wUim8gPOyu",
    "470": "RT @aanya37888: Hii\n Do you like me.. https://t.co/3GlOAooE7K",
    "471": "RT @nahi0910: Say hi if I made you look https://t.co/J1guHmpYOm",
    "472": "Can I inbox you my number???? https://t.co/NfeXgU4h5V",
    "473": "Hi\nAre you free???\n\n#facebook https://t.co/FN90buwULE",
    "474": "RT @ananyas94: I need a male best friend \u2661anyone? \ud83e\udd7a\u2665\ufe0f https://t.co/ShtMNB0Tid",
    "475": "RT @manisha838: Hii\n Do you like me.. https://t.co/8vB5SrTWJ5",
    "476": "RT @rinaku738892: I need a male best friend \u2661anyone? \ud83e\udd7a\u2665\ufe0f https://t.co/GpHmUcdUAa",
    "477": "RT @aanya37888: Say hi if I made you look https://t.co/W3vDdj02g2",
    "478": "Hii\n Do you like me.. https://t.co/or6BZ73Xse",
    "479": "RT @Sofia93947: Say hi if I made you look https://t.co/yPEB4ZIyC2",
    "480": "Hii\n Do you like me.. https://t.co/S24VO3S7EY",
    "481": "RT @nahi0910: Hii\n Do you like me.. https://t.co/EsIQO579Bv",
    "482": "RT @nahi0910: Say hi if I made you look https://t.co/YJ42LtqRtT",
    "483": "RT @aanya37888: Can I inbox you my number???? https://t.co/Wf1PaYlJwZ",
    "484": "RT @rinaku738892: I'm 50+\n\nCome to my house ji \ud83c\udfe1.....\u2763\ufe0f https://t.co/ki9a0ukRVf",
    "485": "RT @ananyas94: I'm 50+\n\nCome to my house ji \ud83c\udfe1.....\u2763\ufe0f https://t.co/hZA4nB49iu",
    "486": "RT @rinaku738892: Say hi if I made you look https://t.co/WkfRnSrEUb",
    "487": "Good morning \ud83c\udf1e https://t.co/rmgPrKf5Ck",
    "488": "Good Night All \u2764\ufe0f https://t.co/KzQ31C8RHh",
    "489": "I am 20+ friendship kroge ji \u2665\ufe0f\u2665\ufe0f https://t.co/75w4rdeth9",
    "490": "RT @nahi0910: Say hi if I made you look https://t.co/d5QhKpYOC1",
    "491": "Do you kiss me \ud83d\udc8b https://t.co/lv1gkPGt5Y",
    "492": "Hii\n Do you like me.. https://t.co/rbpVA7pY1e",
    "493": "Hii\n Do you like me https://t.co/KXfBgR0zLl",
    "494": "RT @manisha838: Hii\n Do you like me.. https://t.co/S24VO3S7EY",
    "495": "RT @aanya37888: Can I inbox you my number???? https://t.co/F6nbq24vFI",
    "496": "RT @ananyas94: Hii\n Do you like me.. https://t.co/LH6IdammNj",
    "497": "Do you love me \u2764\ufe0f\ud83d\udc9e\n\n#kissme https://t.co/MDIQ5LBkbT",
    "498": "RT @rinaku738892: Can I inbox you my number???? https://t.co/ZfoeLWuz96",
    "499": "I need a bed partner \ud83d\udc96\ud83d\udc93 https://t.co/CxFDsmdLaR",
    "500": "RT @manisha838: Say hi if I made you look https://t.co/h2JPE2KYj7",
    "501": "RT @aanya37888: Say hi if I made you look https://t.co/cXI0xqabef",
    "502": "RT @aanya37888: Can I inbox you my number???? https://t.co/3ml5HSAYQc",
    "503": "Hiii ..\nWatsapp ya Facebook? https://t.co/tpJYgXcbXu",
    "504": "RT @rinaku738892: Hii\n Do you like me.. https://t.co/xBAfIxDzVp",
    "505": "RT @rinaku738892: I need a male best friend \u2661anyone? \ud83e\udd7a\u2665\ufe0f https://t.co/NDuLXe4Wbk",
    "506": "RT @rinaku738892: I need a male best friend \u2661anyone? \ud83e\udd7a\u2665\ufe0f https://t.co/Qu2Y9LQ1yL",
    "507": "I need a male best friend \u2661anyone? https://t.co/jK2PJlmXUs",
    "508": "Say hi if I made you look https://t.co/XluMVJE4Ml",
    "509": "RT @nahi0910: Say hi if I made you look https://t.co/LT1g2bjLuZ",
    "510": "Say hi if I made you look https://t.co/R0PlmM6a39",
    "511": "Can I inbox you my number???? https://t.co/dP9HRf5uIX",
    "512": "RT @aanya37888: Hii\n Do you like me.. https://t.co/X4xURXM5Ks",
    "513": "RT @aanya37888: Say hi if I made you look https://t.co/MJD0HV2hzM",
    "514": "Send me your number ?\n\n#facebook https://t.co/jJe3AuXbyA",
    "515": "RT @ananyas94: Say hi if I made you look https://t.co/zQB1kpBuAc",
    "516": "RT @nahi0910: Hii\n Do you like me.. https://t.co/cXhE1rj4lR",
    "517": "RT @nahi0910: Say hi if I made you look https://t.co/W9P47rNJcb",
    "518": "Hii\n Do you like me https://t.co/OneAxKpq4U",
    "519": "Hii\n Do you like me.. https://t.co/8vB5SrTWJ5",
    "520": "RT @Sofia93947: Hii\n Do you like me.. https://t.co/47hreqemmH",
    "521": "Hii\n Do you like me https://t.co/OUgAUo0C5p",
    "522": "RT @Sofia93947: Say hi if I made you look https://t.co/5wDYH3JJ6N",
    "523": "Hii\n Do you like me https://t.co/ngLN4npRzR",
    "524": "Do you kiss me \ud83d\udc8b https://t.co/RR7NG0tRHX",
    "525": "RT @ananyas94: Hii\n Do you like me.. https://t.co/1hEFC9vlxx",
    "526": "RT @nahi0910: Can we chat on WhatsApp??\n\u2764\ufe0f\u2763\ufe0f https://t.co/h1oGXpjvlv",
    "527": "RT @manisha838: Can I inbox you my number???? https://t.co/1jtfVTRXNo",
    "528": "Hii\n Do you like me.. https://t.co/rcQRV3KVdL",
    "529": "RT @aanya37888: Say hi if I made you look https://t.co/L64CsYVSGE",
    "530": "RT @nahi0910: Hii\n Do you like me.. https://t.co/bchGlx5V77",
    "531": "Hii\n Do you like me https://t.co/s2N7tNfFti",
    "532": "RT @manisha838: Can I inbox you my number???? https://t.co/K5oULWl8O0",
    "533": "Do you love me \u2764\ufe0f\ud83d\udc9e\n\n#kissme https://t.co/A4bQmUTRVo",
    "534": "RT @aanya37888: I'm 50+\n\nCome to my house ji \ud83c\udfe1.....\u2763\ufe0f https://t.co/oEbcQHg6AM",
    "535": "Are you 18+ ?\n\n#Facebook https://t.co/bnLRAVe0EL",
    "536": "Aaj Sharma gai mai\ud83d\udc8b https://t.co/GgrzTXLjzb",
    "537": "RT @rinaku738892: Say hi if I made you look https://t.co/cDOmwgynbt",
    "538": "RT @ananyas94: Say hi if I made you look https://t.co/dGBhLOWHag",
    "539": "RT @aanya37888: Say hi if I made you look https://t.co/Xsz2O5Htpj",
    "540": "Can I call you \ud83d\udcde https://t.co/YhMPBeeLB8",
    "541": "https://t.co/NiObCR57A2",
    "542": "RT @ananyas94: Say hi if I made you look https://t.co/SNAy3hcTBb",
    "543": "Ab kya Krna chahte ho\ud83d\udca6\ud83d\udca6\ud83d\udca6 https://t.co/14N0yd0fDA",
    "544": "RT @anie32200: Me or a Mysterious Gift?\ud83d\udea8\ud83c\udf52\ud83d\udc8b https://t.co/RNt2aBitpr",
    "545": "Hii\n Do you like me.. https://t.co/Z1CJECTaHw",
    "546": "Are you 18+ ?\n\n#Facebook https://t.co/qYvjYf2kIy",
    "547": "Hii\n Do you like me.. https://t.co/8R7GVocybY",
    "548": "1 am 45+.. friendship kroge... https://t.co/AGKu42fnz9",
    "549": "I need a HOT bedroom partner\ud83d\udd25\ud83d\udd25 https://t.co/7oupGuukoR",
    "550": "Send me your number \ud83d\udcde https://t.co/lFc9W8z2yK",
    "551": "RT @rinaku738892: Can we chat on WhatsApp??\n\u2764\ufe0f\u2763\ufe0f https://t.co/ZT7KHm4Ig4",
    "552": "Say hi if I made you look https://t.co/j5im8GLxIF",
    "553": "Say hi if I made you look https://t.co/BWVC4y6PHJ",
    "554": "RT @nahi0910: I'm 50+\n\nCome to my house ji \ud83c\udfe1.....\u2763\ufe0f https://t.co/EU800gOxmk",
    "555": "Aaj Sharma gai mai\ud83d\udc8b https://t.co/JE4R0ZAtTv",
    "556": "RT @aanya37888: I like married men\ud83d\udc96\ud83d\udd25\n\n#Facebook https://t.co/eLSQQbOy2k",
    "557": "RT @manisha838: I'm 50+\n\nCome to my house ji \ud83c\udfe1.....\u2763\ufe0f https://t.co/cWz4wawrgR",
    "558": "Hii\n Do you like me https://t.co/pz4Sds8gcd",
    "559": "RT @nahi0910: Say hi if I made you look https://t.co/3dqr9TC6aJ",
    "560": "RT @ananyas94: Say hi if I made you look https://t.co/Zs31d3uA5q",
    "561": "You can enjoy with me \ud83d\udc93 https://t.co/wvxoTbzg4E",
    "562": "Hii\n Do you like me.. https://t.co/4tOYw0XGUe",
    "563": "RT @anie32200: Put a \ud83d\udc30 and I\u2019ll DM you an Easter \ud83d\udc23 gift!! (Today only) https://t.co/GZEEWUGqmk",
    "564": "Say hi if I made you look https://t.co/Du28rgFx01",
    "565": "RT @ananyas94: I'm 50+\n\nCome to my house ji \ud83c\udfe1.....\u2763\ufe0f https://t.co/XUVsa9KUws",
    "566": "Hii\n Do you like me.. https://t.co/WrYee6BNE5",
    "567": "Are you 18+ ?\n\n#Facebook https://t.co/R0aqwXDTT3",
    "568": "Can I inbox you my number???? https://t.co/wJsFgZypiC",
    "569": "Are you 18+ ?\n\n#facebook https://t.co/yiBYTmD4Xs",
    "570": "RT @ananyas94: Can I inbox you my number???? https://t.co/FdfhnzrJKu",
    "571": "You can enjoy with me \ud83d\udc93 https://t.co/sWDrpm0tW9",
    "572": "RT @ananyas94: Hii\n Do you like me.. https://t.co/pNAzci0xm5",
    "573": "RT @manisha838: Say hi if I made you look https://t.co/SlsmewYZjC",
    "574": "RT @manisha838: Can we chat on WhatsApp??\n\u2764\ufe0f\u2763\ufe0f https://t.co/QQJRfhuegO"
}