{
    "0": "RT @Allye95697360: \"Enjin 2040 Community\" \ud83d\udc09\ud83d\udc09\ud83d\udc09 #DragonBrothers  #NFTCommunity Creator @Alfo_nel Choose Winners in 72hrs \u270c\ufe0f\ud83e\udd29\ud83d\ude01\ud83d\udc9c\n\u23f0\ufe0f\u2764\ufe0f&amp;RT\n\u23f0\ufe0fFoll\u2026",
    "1": "RT @gangversenft: \ud83c\udf81 GANGVERSE  X  Project Ishin GIVEAWAY \ud83c\udf81\n\n\ud83c\udfc6 Prizes:  2X Chibi Ishin NFTs\n\n1\u20e3 RT &amp; Tag 3 Frens\n2\u20e3 Follow  @Gangverse + @La\u2026",
    "2": "RT @ade_shina01: \ud83c\udf81 Mega INJECTIVE #NFT Giveaway \ud83c\udf81\n\n15  OG SPOTS\n\nTo Qualify \n\n\ud83e\udd77 Like + Retweet \n\n\ud83e\udd77Follow @injecteriaNFTs and @ade_shina01\u2026",
    "3": "RT @digi_caps: \ud83c\udf89\ud83e\udd73Secondary Sale Giveaway \ud83e\udd73\ud83c\udf89\n\nBuy 2 Secondary Raiders and choose 1 Raider owned by Digi Caps for FREE!\n\nWant to take part in\u2026",
    "4": "RT @ThomasDAO_: Thomas DAO x YeeHaw 3x WL spots\n\nTo Enter:\n\n1) Follow @TheYeeHaw &amp; @ThomasDAO_\n2) Like &amp; RT\n3) Tag 3 frens \n\nWinners out in\u2026",
    "5": "RT @AptosEkosistem: \ud83c\udf81Aptos Watcherz Nft \u00c7ekili\u015fi\n\n\ud83c\udfc63 adet Wl (Free Mint)\n\n \u00c7ekili\u015f \u015fartlar\u0131\ud83d\udd3d\n\n\u2705Takip et\n@AptosEkosistem\u2795@AptosWatcherz\n\u2705Dis\u2026",
    "6": "RT @FrenchiePunk: Simple, Cute, and Totally Worth It - That's Puppy Crypto Art\n\n1)  Drop your eth adress to get some of  Puppy Airdrop\n\n2)\u2026",
    "7": "RT @dr_freak1998: \ud83e\uddea\"Teenagers\"#Giveaway \u30a4\u30d9\u30f3\u30c8\ud83e\uddea\n\n\u4ee5\u4e0b\u306e\u30b5\u30f3\u30d7\u30ebTeenager\u00d73\u540d\u69d8\u306b\u30d7\u30ec\u30bc\u30f3\u30c8\u81f4\u3057\u307e\u3059\ud83c\udf81\n\n\u30fb\u53c2\u52a0\u65b9\u6cd5\n\u2705\u5f53\u30a2\u30ab\u30a6\u30f3\u30c8\u3092\u30d5\u30a9\u30ed\u30fc\n\u2705@chimeraart1130 \u3092\u30d5\u30a9\u30ed\u30fc\n\u2705\u3053\u306e\u30c4\u30a4\u30fc\u30c8\u306e\u3044\u3044\u306d\uff06\u30ea\u30c4\u30a4\u30fc\u30c8\u2026",
    "8": "RT @BoringApesOG: Want to win Boring Apes OG #272? \ud83c\udfc6\n\n\u2705Follow @BoringApesOG\n\u2705Like &amp; Reshare\n\u2705Tag 3 @0xPolygon OGs\n\n #BAOG #NFTGiveaways #Po\u2026",
    "9": "RT @yurosako: \ud83c\udf81 AZURONG #GIVEAWAY\n\nPrizes:\n\ud83c\udfc6 1x AZURONG NFT (Coming soon)\n\nTo Win:\ud83d\udc47\n1\u20e3 Follow @yurosako\n2\u20e3 Tag 4 Friends\n3\u20e3 Like &amp; Retweet\u2026",
    "10": "RT @Gem_titan09: Free #NFT giveaway \ud83c\udf89\n\nFor Random follower\nFollow, like, rt \nTag 3 frnds\n\nEnds at 40 RT\n\n#NFTdrops #NFTGiveaways #NFTs\n#ETH\u2026",
    "11": "RT @communi_teez: \ud83d\ude80Presale Sold out\ud83d\ude80\n\n2nd phase Minting soon!\n\u2764\ufe0fWL = 55\u20b3\n\u2764\ufe0fPublic =120\u20b3\n WL-555 supply\nFor a chance to win WL\nRules\ud83d\udc47\n\ud83d\udc49Tag 3\u2026",
    "12": "RT @ChiaGodsNFT: \ud83c\udf31Time for another #NFTGiveaways! We are giving away one Chellyz NFT @HYP3RH3X\ud83c\udf31. To enter:\n\ud83e\udd47Like and RT this post\n\ud83e\udd48Follow @\u2026",
    "13": "RT @OlafRiche: \ud83c\udf81 Mega INJECTIVE #NFT Giveaway \ud83c\udf81\n\n15  OG SPOTS FREE MINTS\n\nTo Qualify \n\n\ud83e\udd77 Like + Retweet \n\n\ud83e\udd77Follow: @OlafRiche &amp; @injecteria\u2026",
    "14": "RT @ThomasDAO_: Hosting a Solana giveaway once we hit 1k\ud83e\udd73\n\n-Rt\n-Tag 3 frens\n- reply saying \u201c\ud83d\udeaa\u201d  for an inv\n\n#solana #nfts #nft #NFTGiveaway\u2026",
    "15": "RT @jpcm2004_nft: You want adopt my Best Friend #330 \ud83d\udc4a\n\nNext #Giveaway the 15 Matic only 1 Ticket \ud83c\udf9f\ufe0f available \ud83d\udd25\u203c\ufe0f\n\n\ud83d\udc4a\ud83d\udc47\ud83d\udc4a\ud83d\udc47\ud83d\udd25\n#OpenSeaCollectio\u2026",
    "16": "RT @mayescobe99: Follow \n@Christo96448412\n\ud83c\udf20\n@Kodi_Leia\n\ud83c\udf20\n@amigo804\n \ud83c\udf20\n@ElmesOne\n \ud83c\udf20\n@MarianBelu22\n\nLeave eth in comments\n\n72 hours to enter\u2026",
    "17": "RT @doonznft: \ud83c\udf81 DOONZ \ud83e\udd1d PURPLEWAVES \ud83c\udf81\n\n\ud83c\udfc6 1 x #Doonz NFT\n\ud83c\udfc6 1 x #ValiantViking NFT\n\ud83c\udfc6 1 x 100 $DNZ\n\n\u2705repost &amp; \u2764\ufe0f\n\u2705follow @doonznft @doonzcoinz\u2026",
    "18": "RT @Gem_titan09: Free #NFT giveaway for farmers:- $PARAM  @ParamLaboratory $TRIP $BLOCK \n\nFor Random follower\nFollow, like, rt \nTag 3 frnds\u2026",
    "19": "RT @ButtsyCommunity: \ud83c\udf51Buttsy x Ice Girlz\ud83e\uddca\n\n\ud83c\udf81Ice Girlz #498\n\nHow to enter:\n\u2705Follow @ButtsyCommunity &amp; @IceGirlzNFT\n\u2705Like + RT\n\u2705Tag 3 friends\u2026",
    "20": "RT @Gustavo47748482: pretend to draw\ud83d\udd8c\ufe0f\ud83d\udd8c\ufe0f\n\n#nftanimatiion #openseaartists #drawingart #web3community #mintablenft #NFT #rarible #NFTdrops #n\u2026",
    "21": "RT @nft_dragonz: Update\ud83d\udc32 + 2 OG and 4 WL GIVEAWAY \ud83c\udf81\n\nWallet submit for OG and WL is opened on Discord\ud83d\ude80\n\n$DEGGZ soon \ud83d\udc40\n\nwhat to do \ud83e\udd37\u200d\u2642\ufe0f?\n\n\u2705S\u2026",
    "22": "RT @Nobita_Cnft: \ud83d\udea8#NFTGiveaways\ud83d\udea8\n\nIn collaboration with AniMorphia and their hand sketched ordinal project, I am giving away\n\nPrizes:\n\ud83d\udcb0$20\u2026",
    "23": "RT @LoopExchange: \ud83c\udf81#NFTgiveaways \u203c\ufe0f\n\nWin\u300cAccelerator\u2013Undead Pizza Delivery\u300d1/1 dynamic #NFT by @DeadNeons\u2013a new @RumbleLegacy champion from\u2026",
    "24": "RT @ThomasDAO_: 1000 members in ONE WEEK!!!\n\nWill be hosting a Sol giveaway to celebrate\ud83c\udf89\n\nCheck bio + Follow to enter\n\n#solana #nfts #nft\u2026",
    "25": "RT @ThomasDAO_: Giving away .5 SOL in the Thomas DAO\n\nTo Enter:\ud83c\udf81\n\n-Follow\n-RT\n-Join the Discord: https://t.co/hxNIqufVMw\n\n#solana #nfts #nf\u2026",
    "26": "RT @BrunoCelestino9: \ud83d\udea8#NFTGiveaways\ud83d\udea8\n\nIn collaboration with @goofs_world we are giving away:\n\n\ud83d\udc40 1 Diamond Pass \ud83c\udf89\n\nMint coming April 1st \n\nT\u2026",
    "27": "RT @ThomasDAO_: Thomas DAO x Demon Town 10x WL spots\n\nTo Enter:\n\n1) Follow @demon_town_ &amp; @ThomasDAO_\n2) Like &amp; RT\n3) Tag 3 frens \n\nWinners\u2026",
    "28": "RT @c77592432: Follow \n@mayescobe99\n\ud83c\udf20\n@Kodi_Leia\n\ud83c\udf20\n@amigo804\n \ud83c\udf20\n@ElmesOne\n \ud83c\udf20\n@MarianBelu22\n\nLeave eth in comments\n\n72 hours to enter \n\n#NFT\u2026",
    "29": "RT @Gustavo47748482: came out like this\ud83d\udd8a\ufe0f\n\n#nftanimatiion #openseaartists #drawingart #web3community #mintablenft #NFT #rarible #NFTdrops #\u2026"
}