{
    "0": "another Sri Lanka #photodump \ud83e\udeac\n\nv\u010dera vy\u0161el ven nov\u00fd @thetapespodcast community only speci\u00e1l \u010d. 3, kter\u00fd jsem nahr\u00e1vala i s videem poprv\u00e9 mimo studio ~ a to rovnou na Sr\u00ed Lance. t\u00e9ma je dost p\u0159\u00edhodn\u00e9, pobav\u00edme se v n\u011bm o cestov\u00e1n\u00ed a to prim\u00e1rn\u011b o tom za oce\u00e1n \u2708\ufe0f\n\npro\u010d pro m\u011b bylo v\u017edy cestov\u00e1n\u00ed tak d\u016fle\u017eit\u00e9? jak\u00e9 jsou moje nejobl\u00edben\u011bj\u0161\u00ed destinace (mo\u017en\u00e1 p\u0159ekvapiv\u011b\ud83e\udd2d)? pro\u010d je pro m\u011b Sr\u00ed Lanka podruh\u00e9 tak tro\u0161ku ho\u0159ko-sladk\u00e1 a taky dost up\u0159\u00edmn\u00fd life update. s p\u0159\u00edsadou p\u00e1r funny z\u00e1\u017eitk\u016f, tip\u016f i my\u0161lenek. \n\nEpizodu najdete u\u017e nyn\u00ed i s videem na herohero.co/thetapes \ud83e\udd70\n\n#cestovani #travels #thetapes #podcast #lifeupdate",
    "1": "j\u00e1, hledaj\u00edc\u00ed, jak\u00fd nejv\u011bt\u0161\u00ed bal\u00edk slun\u00ed\u010dka se v\u00e1m pokus\u00edm p\u0159\u00ed\u0161t\u00ed t\u00fdden dov\u00e9zt do \u010ceska \ud83c\udf1e\ud83c\udf34",
    "2": "sunday trip to Weligama \ud83e\udde2\ud83c\udfdd\ufe0f\n\n& fav spots: @nomadsrilanka & @ceylonsliders",
    "3": "christmas in vienna\ud83c\udf84 >>>\n\njeliko\u017e jsem z Brna, tak jsme od mali\u010dka jezdili na trhy do V\u00eddn\u011b v\u00edcem\u00e9n\u011b ka\u017ed\u00fd rok a v\u017edycky to byla tot\u00e1ln\u00ed srdcovka. tak\u017ee dne\u0161ek je docela pln\u00fd nostalgie, promrzl\u00fdch tv\u00e1\u0159\u00ed a kone\u010dn\u011b i n\u011bjak\u00e9 t\u00e9 v\u00e1no\u010dn\u00ed atmosf\u00e9ry \ud83d\udc9a\n\nv jak\u00e9m m\u011bst\u011b m\u00e1te r\u00e1di v\u00e1no\u010dn\u00ed trhy vy? budu r\u00e1da za ka\u017ed\u00fd tip \ud83d\udcab",
    "4": "a pokud se nezalekla v\u011bt\u0161\u00edch vln, u\u010d\u00ed se sj\u00ed\u017ed\u011bt ty zelen\u00e9 dote\u010f (a asi i napo\u0159\u00e1d, but I love it) \ud83c\udfc4\ud83c\udffc\u200d\u2640\ufe0f\ud83c\udf0a",
    "5": "Sri Lanka in 0.5 \ud83d\udc4b\ud83c\udffc\ud83e\udd8b\n\n1. Every sesh is a sweat sesh here\n2. Post-surf high\n3. Palmi\u010dky palmi\u010dky palmi\u010dky\n4. Pravideln\u00e1 hodinka s kn\u00ed\u017ekou & tanning sesh\n5. Ice coffee queen\n6. Pre-class morning caffeine\n7. Snackkkkk \ud83c\udf4c",
    "6": "happy birthday to my best friend forever \ud83d\udc36\ud83e\ude77",
    "7": "what a blast \ud83e\udea9\n\nthank you @ca for such an amazing time in Vienna with such a great group! \ud83e\udd70\n\n#makeitanoccasion #vienna #christmas"
}