{
    "0": "hope we learned from my experience. Thank you and goodnight from my side of the world #endurancegrand",
    "1": "Opreation look for the artist of this song I\u2019ll be looking for him too\ud83e\udd79 #endurancegrand",
    "2": "\ud83d\ude02\ud83d\ude02\ud83d\ude02\ud83d\ude02she take care of the house but to shawa is a big problem to her\ud83d\ude2d\ud83d\ude2d",
    "3": "Come make we laugh",
    "4": "#ebubeobio #realbossbaby #uchenancy #faithduke #uchenancytv #nigerianmovies #fyp #viral",
    "5": "Active doings ! #endurancegrand",
    "6": "\ud83d\udd25\ud83d\udd25\ud83d\udd25\ud83d\udd25\ud83d\udd25",
    "7": "The Challenge is Still On. If you Can Do Better drop a Comment \u203c\ufe0f",
    "8": "Best video today",
    "9": "You come for her you collect \ud83d\ude05\ud83d\ude05\ud83d\ude05\ud83d\ude05she come for you, u still going to collect \ud83d\ude05\ud83d\ude05\ud83d\ude05\ud83d\ude05is the end for me\ud83e\udd23\ud83e\udd23",
    "10": "\ud83d\ude02\ud83d\ude02\ud83d\ude02\ud83d\ude02#viralreels #fyp\u30b7\u309aviral #fyp #viral #heartbroken",
    "11": "Her baby daddy called and this happens \ud83d\ude2d\ud83d\ude2d\ud83d\ude2d\ud83d\ude29\ud83d\ude29",
    "12": "Come let look at this \ud83d\ude02",
    "13": "Huge reward",
    "14": "Madam allow oga to enter town hall now \ud83e\udd23\ud83e\udd23"
}