{
    "0": "#compassion #data #foryou ",
    "1": "#led #light #tiktokshop #affiliatemarketing ",
    "2": "#fish #speed #compassion #foryou ",
    "3": "#compassion #foryou #transformers #optimusprime #bumblebee ",
    "4": "#compassion #foryou #marvel #data ",
    "5": "Watch to find out and be amazed by the extraordinary powers of these remarkable characters! Don\u2019t forget to like, share and subscribe for more thrilling Marvel content! Excelsior #compassion #foryou #marvel #data ",
    "6": "#comparison #data #foryou #speed #3d #animals ",
    "7": "#databall #3d #comparison #foryou ",
    "8": "#beer #tiktokshop #blackfridaysale #sale #affiliatemarketing ",
    "9": "#comparison #data #foryou #data #speed ",
    "10": "Replying to @Micah. #databall #3d #comparison #foryou #world #size ",
    "11": "#comparison #data #foryou #3d #speed #animals ",
    "12": "#compassion #foryou #eyes ",
    "13": "#compassion #marvel #data #foryou ",
    "14": "#comparison #data #foryou #3d ",
    "15": "#tidewe #men #hunting #jacket #tiktokshop #blackfridaysale ",
    "16": "#comparison #data ",
    "17": "#comparison #data #foryou ",
    "18": "#comparison #data #foryou #marvel #mcu #3d ",
    "19": "Buy goods to support the channel #comparison #data ",
    "20": "#databall #3d #comparison #foryou #world #size ",
    "21": "A $20 dash cam could save you thousands if someone hits you and you have to prove it. Man, i hate dealing with insurance lol #dashcam #dashcamvideos #dash #dashcamtech #tiktokshop #blackfridaysale #camera "
}