{
    "0": "\u0102n hay \u0111\u1ed7 ? \ud83e\udd79 #xuhuong #tiktokfood #muckbang ",
    "1": "#xuhuong #tiktok #muckbang ",
    "2": "#xuhuong #tiktokfood #muckbang ",
    "3": "#tiktokfood #bayashi #asmr #food #viral #fyp #foryou #fans ",
    "4": "#tiktokfood #bayashi #asmr #food #viral #fyp #foryou #fans",
    "5": "#tiktokfood #bayashi #asmr #food #fans #viral #foryou #fyp ",
    "6": "Have breakfast with me.#xuhuong #tiktok #muckbang ",
    "7": "Have dinner with me. \ud83d\ude40 #xuhuong #tiktok #muckbang ",
    "8": "#tiktokfood #bayashi  #asmr  #food  #viral  #fyp  #foryou  #fans",
    "9": "Hi You! #Master2023byTikTok #TikTokFashion #xuhuong #tiktok #muckbang ",
    "10": "Hi friends #xuhuong #tiktok #muckbang #anh ",
    "11": "Mlemmm \ud83d\ude1c #xuhuong #tiktok #muckbang ",
    "12": "Sad \ud83d\ude40 #xuhuong #tiktok #muckbang ",
    "13": "#goodfood #tiktokfood #food #amazing #foryou #viral #viraltiktok ",
    "14": "T\u00d4M H\u00d9M NH\u1eacT\ud83e\udd9e  #xuhuong #tiktokfood #muckbang ",
    "15": "With me \ud83c\udf1d #TikTokFashion #xuhuong #tiktok #muckbang ",
    "16": "Chicken \ud83d\udc25 #xuhuong #tiktokfood #muckbang "
}